ckanext/__init__.py
ckanext/selfinfo/__init__.py
ckanext/selfinfo/config.py
ckanext/selfinfo/config_declaration.yaml
ckanext/selfinfo/handlers.py
ckanext/selfinfo/helpers.py
ckanext/selfinfo/interfaces.py
ckanext/selfinfo/plugin.py
ckanext/selfinfo/utils.py
ckanext/selfinfo/assets/script.js
ckanext/selfinfo/assets/style.css
ckanext/selfinfo/assets/webassets.yml
ckanext/selfinfo/assets/css/vendor/datatables.css
ckanext/selfinfo/assets/css/vendor/jquery.ui.datepicker.css
ckanext/selfinfo/assets/js/datepicker.js
ckanext/selfinfo/assets/js/reset-module-last-check.js
ckanext/selfinfo/assets/js/search-through-content.js
ckanext/selfinfo/assets/js/search-through-table.js
ckanext/selfinfo/assets/js/vendor/datatables.min.js
ckanext/selfinfo/assets/js/vendor/jquery.ui.datepicker.js
ckanext/selfinfo/cli/__init__.py
ckanext/selfinfo/cli/main.py
ckanext/selfinfo/logic/__init__.py
ckanext/selfinfo/logic/action/__init__.py
ckanext/selfinfo/logic/action/delete.py
ckanext/selfinfo/logic/action/get.py
ckanext/selfinfo/logic/action/update.py
ckanext/selfinfo/public/.gitignore
ckanext/selfinfo/public/images/ui-icons_444444_256x240.png
ckanext/selfinfo/public/images/ui-icons_555555_256x240.png
ckanext/selfinfo/public/images/ui-icons_777620_256x240.png
ckanext/selfinfo/public/images/ui-icons_777777_256x240.png
ckanext/selfinfo/public/images/ui-icons_cc0000_256x240.png
ckanext/selfinfo/public/images/ui-icons_ffffff_256x240.png
ckanext/selfinfo/templates/selfinfo/header.html
ckanext/selfinfo/templates/selfinfo/index.html
ckanext/selfinfo/templates/selfinfo/scripts/selfinfo_custom_scripts.html
ckanext/selfinfo/templates/selfinfo/snippets/additional_content_tabs.html
ckanext/selfinfo/templates/selfinfo/snippets/additional_navigation_tabs.html
ckanext/selfinfo/templates/selfinfo/snippets/ckan_queues.html
ckanext/selfinfo/templates/selfinfo/snippets/self_actions.html
ckanext/selfinfo/templates/selfinfo/snippets/self_auth_actions.html
ckanext_selfinfo-2.0.0.dist-info/licenses/LICENSE
ckanext_selfinfo-2.0.0.dist-info/METADATA
ckanext_selfinfo-2.0.0.dist-info/WHEEL
ckanext_selfinfo-2.0.0.dist-info/entry_points.txt
ckanext_selfinfo-2.0.0.dist-info/top_level.txt
ckanext_selfinfo-2.0.0.dist-info/RECORD
