Metadata-Version: 2.4
Name: ckanext-selfinfo
Version: 2.0.0
Summary: Web based Sys Admin server statistics
Author-email: DataShades <datashades@linkdigital.com.au>, Yan R <yan.rudenko@linkdigital.com.au>
Maintainer-email: DataShades <datashades@linkdigital.com.au>, Engerrs <datashades@linkdigital.com.au>
License: MIT
Project-URL: Homepage, https://github.com/DataShades/ckanext-selfinfo
Keywords: CKAN
Classifier: Development Status :: 4 - Beta
Classifier: License :: OSI Approved :: MIT License
Classifier: Programming Language :: Python :: 3.8
Classifier: Programming Language :: Python :: 3.9
Classifier: Programming Language :: Python :: 3.10
Classifier: Programming Language :: Python :: 3.11
Classifier: Programming Language :: Python :: 3.12
Requires-Python: >=3.8
License-File: LICENSE
Requires-Dist: prettytable>=3.10.0
Requires-Dist: psutil>=7.0.0
Requires-Dist: GitPython>=3.1.32
Requires-Dist: distro>=1.9.0
Requires-Dist: cryptography>=44.0.2
Requires-Dist: pip>=21.0.0
Provides-Extra: docs
Requires-Dist: mkdocs; extra == "docs"
Requires-Dist: mkdocs-material; extra == "docs"
Requires-Dist: mkdocstrings[python]; extra == "docs"
Requires-Dist: mkdocs-glightbox==0.4.0; extra == "docs"
Provides-Extra: test
Requires-Dist: pytest-ckan; extra == "test"
Requires-Dist: junit2html==31.0.2; extra == "test"
Dynamic: license-file
